MANIFEST.in
setup.py
infozuild/__init__.py
infozuild/daemon.ini
infozuild/daemon.py
infozuild/getscript.py
infozuild/motds.txt
infozuild/sendscript.py
infozuild.egg-info/PKG-INFO
infozuild.egg-info/SOURCES.txt
infozuild.egg-info/dependency_links.txt
infozuild.egg-info/entry_points.txt
infozuild.egg-info/not-zip-safe
infozuild.egg-info/requires.txt
infozuild.egg-info/top_level.txt