Metadata-Version: 1.1
Name: infozuild
Version: 0.8.2
Summary: daemon and scripts for updating the infozuil
Home-page: https://github.com/svsticky/information-column
Author: Study Association Sticky
Author-email: info@svsticky.nl
License: MIT
Platform: UNKNOWN
Classifier: Development Status :: 4 - Beta
Classifier: License :: OSI Approved :: MIT License
Classifier: Environment :: Console
Classifier: Programming Language :: Python :: 3
Classifier: Programming Language :: Python :: 3.3
Classifier: Programming Language :: Python :: 3.4
Classifier: Programming Language :: Python :: 3.5
Classifier: Programming Language :: Python :: 3 :: Only
